popcat_wrapper/__init__.py
popcat_wrapper/popcat_wrapper.py
popcat_wrapper/utils.py
popcat_wrapper-1.5.dist-info/LICENSE
popcat_wrapper-1.5.dist-info/METADATA
popcat_wrapper-1.5.dist-info/WHEEL
popcat_wrapper-1.5.dist-info/top_level.txt
popcat_wrapper-1.5.dist-info/RECORD
