Metadata-Version: 2.1
Name: popcat-wrapper
Version: 1.5
Summary: A wrapper designed for easy image manipulation
Home-page: https://github.com/NotFaizen/popcat_wrapper
Author: NotFaizen
Author-email: munavir370@gmail.com
License: UNKNOWN
Keywords: python,async,popcat,popcatapi,api,api wrapper,discord,wrapper
Platform: UNKNOWN
Classifier: Programming Language :: Python :: 3
Classifier: License :: OSI Approved :: MIT License
Classifier: Operating System :: OS Independent
Requires-Python: >=3.6
Requires-Dist: aiohttp
